mecat/DATE.py
mecat/__init__.py
mecat/evaluate.py
mecat/scorer.py
mecat/utils.py
mecat/reference/caption/test/000.jsonl.gz
mecat/reference/caption/test/00A.jsonl.gz
mecat/reference/caption/test/0M0.jsonl.gz
mecat/reference/caption/test/0MA.jsonl.gz
mecat/reference/caption/test/S00.jsonl.gz
mecat/reference/caption/test/S0A.jsonl.gz
mecat/reference/caption/test/SM0.jsonl.gz
mecat/reference/caption/test/SMA.jsonl.gz
mecat/reference/qa/test/000.jsonl.gz
mecat/reference/qa/test/00A.jsonl.gz
mecat/reference/qa/test/0M0.jsonl.gz
mecat/reference/qa/test/0MA.jsonl.gz
mecat/reference/qa/test/S00.jsonl.gz
mecat/reference/qa/test/S0A.jsonl.gz
mecat/reference/qa/test/SM0.jsonl.gz
mecat/reference/qa/test/SMA.jsonl.gz
mecat-1.1.0.dist-info/licenses/LICENSE
mecat-1.1.0.dist-info/METADATA
mecat-1.1.0.dist-info/WHEEL
mecat-1.1.0.dist-info/entry_points.txt
mecat-1.1.0.dist-info/top_level.txt
mecat-1.1.0.dist-info/RECORD
