Metadata-Version: 2.4
Name: mecat
Version: 1.1.0
Summary: Multi-Expert Chain for Audio Tasks (MECAT)
Author-email: Yadong Niu <niuyadong@xiaomi.com>, Tianzi Wang <twang@se.cuhk.edu.hk>, Heinrich Dinkel <dinkelheinrich@xiaomi.com>, Xingwei Sun <sunxingwei@xiaomi.com>, Jiahao Zhou <zhoukz@bupt.edu.cn>, Gang Li <ligang5@xiaomi.com>, Jizhong Liu <liujizhong1@xiaomi.com>, Junbo Zhang <zhangjunbo1@xiaomi.com>, Jian Luan <luanjian@xiaomi.com>
Project-URL: Repository, https://git.n.xiaomi.com/niuyadong/mecat_public.git
Requires-Python: >=3.10
License-File: LICENSE
Requires-Dist: loguru
Requires-Dist: numpy
Requires-Dist: tabulate
Requires-Dist: datasets
Requires-Dist: torch>=2.2.1
Requires-Dist: pandas
Requires-Dist: transformers>=4.52.4
Requires-Dist: tqdm
Requires-Dist: sentence_transformers>=4.1
Requires-Dist: requests
Requires-Dist: psutil
Dynamic: license-file
